heartbeatmonitor/__init__.py
heartbeatmonitor/heartbeat.py
heartbeatmonitor/monitor.py
heartbeatmonitor-0.1a18.dist-info/METADATA
heartbeatmonitor-0.1a18.dist-info/RECORD
heartbeatmonitor-0.1a18.dist-info/WHEEL
heartbeatmonitor-0.1a18.dist-info/top_level.txt
