Metadata-Version: 2.1
Name: heartbeatmonitor
Version: 0.1a18
Summary: Central heartbeat monitoring application for multi-program deployment.
Home-page: https://github.com/hmallen/heartbeatmonitor
Author: Hunter M. Allen
Author-email: allenhm@gmail.com
License: MIT
Keywords: heartbeat,monitor
Platform: UNKNOWN
Classifier: Programming Language :: Python :: 3
Classifier: License :: OSI Approved :: MIT License
Classifier: Operating System :: OS Independent
Requires-Dist: python-dateutil (>=2.7.3)
Requires-Dist: slackclient (>=1.2.1)
